SpringBatch41ZhongwenWendang/README.md
SpringBatch41ZhongwenWendang/__init__.py
SpringBatch41ZhongwenWendang/__main__.py
SpringBatch41ZhongwenWendang/file.epub
SpringBatch41ZhongwenWendang/index.html
SpringBatch41ZhongwenWendang/css/__init__.py
SpringBatch41ZhongwenWendang/css/annotations.css
SpringBatch41ZhongwenWendang/css/main.css
SpringBatch41ZhongwenWendang/css/normalize.css
SpringBatch41ZhongwenWendang/css/popup.css
SpringBatch41ZhongwenWendang/font/__init__.py
SpringBatch41ZhongwenWendang/font/fontello.eot
SpringBatch41ZhongwenWendang/font/fontello.svg
SpringBatch41ZhongwenWendang/font/fontello.ttf
SpringBatch41ZhongwenWendang/font/fontello.woff
SpringBatch41ZhongwenWendang/img/__init__.py
SpringBatch41ZhongwenWendang/img/annotator-glyph-sprite.png
SpringBatch41ZhongwenWendang/img/annotator-icon-sprite.png
SpringBatch41ZhongwenWendang/img/apple-touch-icon.png
SpringBatch41ZhongwenWendang/img/cancelfullscreen.png
SpringBatch41ZhongwenWendang/img/close.png
SpringBatch41ZhongwenWendang/img/fullscreen.png
SpringBatch41ZhongwenWendang/img/loader.gif
SpringBatch41ZhongwenWendang/img/menu-icon.png
SpringBatch41ZhongwenWendang/img/save.png
SpringBatch41ZhongwenWendang/img/saved.png
SpringBatch41ZhongwenWendang/img/settings-s.png
SpringBatch41ZhongwenWendang/img/settings.png
SpringBatch41ZhongwenWendang/img/star.png
SpringBatch41ZhongwenWendang/js/__init__.py
SpringBatch41ZhongwenWendang/js/epub.js
SpringBatch41ZhongwenWendang/js/epub.min.js
SpringBatch41ZhongwenWendang/js/epub.min.map
SpringBatch41ZhongwenWendang/js/hooks.min.js
SpringBatch41ZhongwenWendang/js/hooks.min.map
SpringBatch41ZhongwenWendang/js/reader.js
SpringBatch41ZhongwenWendang/js/reader.js.map
SpringBatch41ZhongwenWendang/js/reader.min.js
SpringBatch41ZhongwenWendang/js/reader.min.map
SpringBatch41ZhongwenWendang/js/hooks/__init__.py
SpringBatch41ZhongwenWendang/js/hooks/extensions/__init__.py
SpringBatch41ZhongwenWendang/js/hooks/extensions/highlight.js
spring_batch_4_1_zhongwen_wendang-2024.3.5.0.dist-info/METADATA
spring_batch_4_1_zhongwen_wendang-2024.3.5.0.dist-info/WHEEL
spring_batch_4_1_zhongwen_wendang-2024.3.5.0.dist-info/entry_points.txt
spring_batch_4_1_zhongwen_wendang-2024.3.5.0.dist-info/top_level.txt
spring_batch_4_1_zhongwen_wendang-2024.3.5.0.dist-info/RECORD
